openwebui_access/__init__.py
openwebui_access/client.py
openwebui_access/messagebuilder.py
openwebui_access-1.0.0.dist-info/licenses/LICENSE
openwebui_access-1.0.0.dist-info/METADATA
openwebui_access-1.0.0.dist-info/WHEEL
openwebui_access-1.0.0.dist-info/top_level.txt
openwebui_access-1.0.0.dist-info/RECORD
