Metadata-Version: 2.4
Name: openwebui-access
Version: 1.0.0
Summary: Open WebUI Access Python Library. See https://github.com/schirmacher/openwebui-access for a tutorial.
Author-email: Arne Schirmacher <arne@schirmacher.de>
License-Expression: GPL-3.0-or-later
Project-URL: Homepage, https://github.com/schirmacher/openwebui-access
Project-URL: Issues, https://github.com/schirmacher/openwebui-access/issues
Classifier: Programming Language :: Python :: 3
Classifier: Operating System :: OS Independent
Requires-Python: >=3.9
License-File: LICENSE
Requires-Dist: requests>=2.32.4
Dynamic: license-file
